jrub/__init__.py
jrub/enums.py
jrub/exceptions.py
jrub/client/__init__.py
jrub/client/client.py
jrub/crypto/__init__.py
jrub/crypto/crypto.py
jrub/methods/__init__.py
jrub/methods/methods.py
jrub/network/__init__.py
jrub/network/helper.py
jrub/network/network.py
jrub/network/socket.py
jrub/sessions/__init__.py
jrub/sessions/sessions.py
jrub/types/__init__.py
jrub/types/socket/__init__.py
jrub/types/socket/message.py
jrub/utils/__init__.py
jrub/utils/configs.py
jrub/utils/utils.py
jrub-1.0.0.dist-info/METADATA
jrub-1.0.0.dist-info/WHEEL
jrub-1.0.0.dist-info/top_level.txt
jrub-1.0.0.dist-info/RECORD
