Metadata-Version: 2.1
Name: jrub
Version: 1.0.0
Summary: rubika bot
Home-page: https://github.com/mahdy-ahmadi/
Author: Mahdi Ahmadi
Author-email: mahdiahmadi.1208@gmail.com
Classifier: Programming Language :: Python :: 3
Classifier: License :: OSI Approved :: MIT License
Classifier: Operating System :: OS Independent
Requires-Python: >=3.6
Requires-Dist: requests
Requires-Dist: urllib3
